CHANGELOG.txt
LICENSE.txt
MANIFEST.in
README.txt
requirements.txt
setup.py
test.py
test_recovery.py
sftpoeb/__init__.py
sftpoeb.egg-info/PKG-INFO
sftpoeb.egg-info/SOURCES.txt
sftpoeb.egg-info/dependency_links.txt
sftpoeb.egg-info/requires.txt
sftpoeb.egg-info/top_level.txt
sftpoeb/config/variable.py
sftpoeb/mainclass/__init__.py
sftpoeb/mainclass/c_recovery.py
sftpoeb/mainclass/c_sftp.py
sftpoeb/method/__init__.py
sftpoeb/method/callservice.py
sftpoeb/method/checkpath.py
sftpoeb/method/debug.py
sftpoeb/method/mail.py
sftpoeb/sftpoeb.egg-info/SOURCES.txt
sftpoeb/sftpoeb.egg-info/dependency_links.txt
sftpoeb/sftpoeb.egg-info/requires.txt
sftpoeb/sftpoeb.egg-info/top_level.txt
sftpoeb/subclass/__init__.py
sftpoeb/subclass/alert/__init__.py
sftpoeb/subclass/alert/s_c_alert.py
sftpoeb/subclass/file/__init__.py
sftpoeb/subclass/file/s_c_file.py
sftpoeb/subclass/file/s_c_file_transfer.py
sftpoeb/subclass/input/__init__.py
sftpoeb/subclass/input/s_c_input.py
sftpoeb/subclass/output/__init__.py
sftpoeb/subclass/output/s_c_output.py
sftpoeb/subclass/path/__init__.py
sftpoeb/subclass/path/s_c_setgetdestination.py
sftpoeb/subclass/path/s_c_setgetlocal.py
sftpoeb/subclass/path/s_c_setgetrecovery.py
sftpoeb/subclass/process/__init__.py
sftpoeb/subclass/process/s_c_process_package_1.py
sftpoeb/subclass/process/s_c_process_package_2.py
sftpoeb/subclass/recovery/__init__.py
sftpoeb/subclass/recovery/s_c_recovery.py