Metadata-Version: 2.1
Name: sftpoeb
Version: 0.2.2
Summary: To Easy create sftp for e-tax invoice & e-receive of Oneeletronicbilling
Home-page: UNKNOWN
Author: Natthawut Thawisombat
Author-email: natthawut.th@inet.co.th
License: MIT
Keywords: sftp
Platform: UNKNOWN
License-File: LICENSE.txt
